README.txt
setup.py
collective/__init__.py
collective.flexibleordering.egg-info/PKG-INFO
collective.flexibleordering.egg-info/SOURCES.txt
collective.flexibleordering.egg-info/dependency_links.txt
collective.flexibleordering.egg-info/entry_points.txt
collective.flexibleordering.egg-info/namespace_packages.txt
collective.flexibleordering.egg-info/not-zip-safe
collective.flexibleordering.egg-info/paster_plugins.txt
collective.flexibleordering.egg-info/requires.txt
collective.flexibleordering.egg-info/top_level.txt
collective/flexibleordering/__init__.py
collective/flexibleordering/configure.zcml
collective/flexibleordering/interfaces.py
collective/flexibleordering/ordering.py
collective/flexibleordering/subscriber.py
collective/flexibleordering/tests.py
docs/HISTORY.txt
docs/INSTALL.txt
docs/LICENSE.GPL
docs/LICENSE.txt