Metadata-Version: 1.1
Name: collective.flexibleordering
Version: 1.0beta1
Summary: A custom folder ordering implementation, which stores order persistently, but sorts content based on a rule.
Home-page: http://svn.plone.org/svn/collective/
Author: UNKNOWN
Author-email: UNKNOWN
License: GPL
Platform: UNKNOWN
Classifier: Framework :: Plone
Classifier: Programming Language :: Python
